src/__about__.py
src/assemble_video.py
src/extract_notes.py
src/generate_videoclips.py
src/pdf2png.py
src/pptx2pdf.py
src/text2speech.py
pptx2video-1.0.0a1.dist-info/METADATA
pptx2video-1.0.0a1.dist-info/WHEEL
pptx2video-1.0.0a1.dist-info/RECORD
