Metadata-Version: 2.1
Name: pptx2video
Version: 1.0.0a1
Summary: Transform PowerPoint presentations to videos with voiceovers.
Project-URL: Documentation, https://github.com/drengskapur/pptx2video#readme
Project-URL: Issues, https://github.com/drengskapur/pptx2video/issues
Project-URL: Source, https://github.com/drengskapur/pptx2video
Author-email: Drengskapur <service@drengskapur.com>
Requires-Python: >=3.7
Requires-Dist: dvc
Requires-Dist: ffmpeg-python
Requires-Dist: natsort
Requires-Dist: openai
Requires-Dist: pdf2image
Requires-Dist: python-dotenv
Requires-Dist: python-pptx
Requires-Dist: tenacity
